[
    {
      "name": "Evaluate",
      "detail": "Our team of experts work with you to assess your existing management practices to understand how you operate.",
      "image": "./evaluate.jpg"
    },
    {
      "name": "Analyze",
      "detail": "We then identify any gaps within the current school operations.",
      "image": "./analyze.jpg"
    },
    {
      "name": "Assessment",
      "detail": "Based on evaluation and analysis we come up with a report of the existing operational practices & how to improve them.",
      "image": "./assessment.jpg"
    },
    {
        "name": "Implementation",
        "detail": "Our team creates effective improvement plans & helps you to implement them to improve operations. This will be based on priority & budget.",
        "image": "./feedback.jpg"
      }
  ]
  